mdms/__init__.py
mdms/amber_parameters.py
mdms/initial_struc.py
mdms/mdms_menu.py
mdms/run_simulations.py
mdms/topology_prep.py
mdms-1.0.4.dist-info/LICENSE
mdms-1.0.4.dist-info/METADATA
mdms-1.0.4.dist-info/WHEEL
mdms-1.0.4.dist-info/entry_points.txt
mdms-1.0.4.dist-info/top_level.txt
mdms-1.0.4.dist-info/RECORD
