Metadata-Version: 2.1
Name: mdms
Version: 1.0.4
Summary: An interface to one of the most popular Molecular Dynamics codes - Amber - which aids user in preparing and running their own simulations.
Home-page: https://github.com/szymonzaczek/MDMS
Author: Szymon Zaczek
Author-email: szymon.zaczek@edu.p.lodz.pl
License: UNKNOWN
Platform: UNKNOWN
Classifier: Programming Language :: Python :: 3
Classifier: License :: OSI Approved :: MIT License
Classifier: Operating System :: POSIX :: Linux
Classifier: Development Status :: 4 - Beta
Classifier: Environment :: Console
Classifier: Intended Audience :: Science/Research
Classifier: Topic :: Scientific/Engineering :: Bio-Informatics
Classifier: Topic :: Scientific/Engineering :: Chemistry
Requires-Dist: numpy
Requires-Dist: pandas
Requires-Dist: biopython
Requires-Dist: pdb-tools
